aiogram_sqlalchemy_storage-0.2.0.post0.dist-info/licenses/LICENSE
sqlalchemy_storage/__init__.py
sqlalchemy_storage/models.py
sqlalchemy_storage/storage.py
aiogram_sqlalchemy_storage-0.2.0.post0.dist-info/METADATA
aiogram_sqlalchemy_storage-0.2.0.post0.dist-info/WHEEL
aiogram_sqlalchemy_storage-0.2.0.post0.dist-info/top_level.txt
aiogram_sqlalchemy_storage-0.2.0.post0.dist-info/RECORD
