Metadata-Version: 2.4
Name: aiogram-sqlalchemy-storage
Version: 0.2.0.post0
Summary: SQLAlchemy-based storage for aiogram FSM
Home-page: https://github.com/meshya/aiogram-sqlalchemy-storage
Author: meshya
Author-email: meshmeshmeshya@gmail.com
Classifier: Programming Language :: Python :: 3
Classifier: License :: OSI Approved :: MIT License
Classifier: Operating System :: OS Independent
Requires-Python: >=3.9
License-File: LICENSE
Requires-Dist: aiogram>=3
Requires-Dist: SQLAlchemy>=2
Dynamic: author
Dynamic: author-email
Dynamic: classifier
Dynamic: description
Dynamic: description-content-type
Dynamic: home-page
Dynamic: license-file
Dynamic: requires-dist
Dynamic: requires-python
Dynamic: summary
